setup.py
distributions/Binomialdistribution.py
distributions/Gaussiandistribution.py
distributions/Generaldistribution.py
distributions/__init__.py
kannan_propability.egg-info/PKG-INFO
kannan_propability.egg-info/SOURCES.txt
kannan_propability.egg-info/dependency_links.txt
kannan_propability.egg-info/not-zip-safe
kannan_propability.egg-info/top_level.txt